django_dynamic_views/models.py
django_dynamic_views/views.py
django_dynamic_views/__init__.py
django_dynamic_views/static/css/django_dynamic_views.css
django_dynamic_views/static/js/django_dynamic_views.js
django_dynamic_views/templates/base.html
django_dynamic_views/templates/django_dynamic_views/admin_dynamic_list_view.html
django_dynamic_views/templates/django_dynamic_views/base.html
django_dynamic_views/templates/django_dynamic_views/dynamic_delete_form.html
django_dynamic_views/templates/django_dynamic_views/dynamic_form.html
django_dynamic_views/templates/django_dynamic_views/dynamic_list_view.html
django_dynamic_views/templates/django_dynamic_views/dynamic_read_view.html
django_dynamic_views/templatetags/get_attribute.py
django_dynamic_views/templatetags/get_class.py
django_dynamic_views/templatetags/get_field_filter.py
django_dynamic_views/templatetags/get_human_range.py
django_dynamic_views/templatetags/get_range.py
django_dynamic_views/templatetags/__init__.py
django_dynamic_views-0.1.1.dist-info/DESCRIPTION.rst
django_dynamic_views-0.1.1.dist-info/METADATA
django_dynamic_views-0.1.1.dist-info/metadata.json
django_dynamic_views-0.1.1.dist-info/RECORD
django_dynamic_views-0.1.1.dist-info/top_level.txt
django_dynamic_views-0.1.1.dist-info/WHEEL
