Metadata-Version: 2.0
Name: django-dynamic-views
Version: 0.1.1
Summary: Provides out of the box CRUD functionality including templates and gives you the ability to build your screen top-down.
Home-page: https://github.com/ddaan/django-dynamic-views
Author: Daan Vielen
Author-email: daan@digitaldaan.nl
License: BSD
Keywords: django-dynamic-views
Platform: UNKNOWN
Classifier: Development Status :: 3 - Alpha
Classifier: Framework :: Django
Classifier: Framework :: Django :: 1.8
Classifier: Framework :: Django :: 1.9
Classifier: Intended Audience :: Developers
Classifier: License :: OSI Approved :: BSD License
Classifier: Natural Language :: English
Classifier: Programming Language :: Python :: 2
Classifier: Programming Language :: Python :: 2.7
Classifier: Programming Language :: Python :: 3
Classifier: Programming Language :: Python :: 3.4
Classifier: Programming Language :: Python :: 3.5
